butter_backup/__init__.py
butter_backup/backup_backends.py
butter_backup/cli.py
butter_backup/config_parser.py
butter_backup/device_managers.py
butter_backup/py.typed
butter_backup-3.5.4.dist-info/METADATA
butter_backup-3.5.4.dist-info/WHEEL
butter_backup-3.5.4.dist-info/entry_points.txt
butter_backup-3.5.4.dist-info/licenses/LICENSE
butter_backup-3.5.4.dist-info/RECORD
