Metadata-Version: 2.4
Name: butter-backup
Version: 3.5.4
Summary: Vollverschlüsselte, pseudoinkrementelle Sicherungskopien leicht gemacht
License-Expression: GPL-3.0-or-later
License-File: LICENSE
Author: Max Görner
Author-email: max@familie-goerner.eu
Requires-Python: >=3.10,<4.0.0
Classifier: Programming Language :: Python :: 3
Classifier: Programming Language :: Python :: 3.10
Classifier: Programming Language :: Python :: 3.11
Classifier: Programming Language :: Python :: 3.12
Classifier: Programming Language :: Python :: 3.13
Classifier: Programming Language :: Python :: 3.14
Provides-Extra: all
Requires-Dist: loguru (>=0.7.3)
Requires-Dist: pydantic (>=2.12.5)
Requires-Dist: rich (>=13.9.4) ; extra == "all"
Requires-Dist: shell-interface (>=1.0.1)
Requires-Dist: storage-device-managers (>=1.0.0)
Requires-Dist: typer (>=0.20.0)
Project-URL: Changelog, https://github.com/MaxG87/ButterBackup/blob/main/CHANGELOG.md
Project-URL: Homepage, https://github.com/MaxG87/ButterBackup
Project-URL: Issues, https://github.com/MaxG87/ButterBackup/issues
Project-URL: Repository, https://github.com/MaxG87/ButterBackup
